rushdb/__init__.py
rushdb/client.py
rushdb/common.py
rushdb/api/__init__.py
rushdb/api/base.py
rushdb/api/labels.py
rushdb/api/properties.py
rushdb/api/query.py
rushdb/api/records.py
rushdb/api/relationships.py
rushdb/api/transactions.py
rushdb/models/__init__.py
rushdb/models/property.py
rushdb/models/record.py
rushdb/models/relationship.py
rushdb/models/result.py
rushdb/models/search_query.py
rushdb/models/transaction.py
rushdb/utils/token_prefix.py
rushdb-1.14.0.dist-info/METADATA
rushdb-1.14.0.dist-info/WHEEL
rushdb-1.14.0.dist-info/licenses/LICENSE
rushdb-1.14.0.dist-info/RECORD
