Metadata-Version: 2.4
Name: rushdb
Version: 1.14.0
Summary: RushDB Python SDK
Project-URL: Homepage, https://github.com/rush-db/rushdb-python
Project-URL: Repository, https://github.com/rush-db/rushdb-python
Project-URL: Documentation, https://docs.rushdb.com
Author-email: RushDB Team <hi@rushdb.com>
License: Apache-2.0
License-File: LICENSE
Keywords: ai,ai database,app backend,app-backend,artificial intelligence,cloud,cypher,data analysis,data engineering,data management,data pipeline,data science,data-analysis,data-engineering,data-management,data-pipeline,data-science,database,db,embedding,embeddings,etl,fractal api,fractal-api,graph,graph database,graph-database,graphs,instant database,instant db,instant-database,instant-db,json normalization,json-normalization,machine learning,machine-learning,modern apps,modern-apps,neo4j,no-s
Requires-Python: >=3.8
Requires-Dist: python-dotenv>=1.0.0
Requires-Dist: requests>=2.31.0
Provides-Extra: dev
Requires-Dist: black>=23.7.0; extra == 'dev'
Requires-Dist: isort>=5.12.0; extra == 'dev'
Requires-Dist: mypy>=1.4.1; extra == 'dev'
Requires-Dist: pytest-cov>=4.1.0; extra == 'dev'
Requires-Dist: pytest>=7.4.0; extra == 'dev'
Requires-Dist: ruff>=0.0.280; extra == 'dev'
Requires-Dist: types-python-dateutil>=2.8.19.14; extra == 'dev'
Requires-Dist: types-requests>=2.31.0.1; extra == 'dev'
